jm_crypto_ciphers/__init__.py
jm_crypto_ciphers-2.0.1.dist-info/WHEEL
jm_crypto_ciphers-2.0.1.dist-info/METADATA
jm_crypto_ciphers-2.0.1.dist-info/RECORD
