Metadata-Version: 2.1
Name: jm-crypto-ciphers
Version: 2.0.1
Summary: Implements various ciphers from the pycryptodome package and some custom ones.
Author: Jonathan Mahaffey
Requires-Python: >=3.8,<4.0
Classifier: Programming Language :: Python :: 3
Classifier: Programming Language :: Python :: 3.8
Classifier: Programming Language :: Python :: 3.9
